neurodec/__init__.py
neurodec/cli/__init__.py
neurodec/cli/argparse.py
neurodec/mdt/__init__.py
neurodec/mdt/auth.py
neurodec/mdt/encoding.py
neurodec-0.0.6.data/scripts/neurodec
neurodec-0.0.6.dist-info/METADATA
neurodec-0.0.6.dist-info/WHEEL
neurodec-0.0.6.dist-info/top_level.txt
neurodec-0.0.6.dist-info/RECORD
